lionchief/__init__.py
lionchief/connection.py
lionchief/lighting.py
lionchief/motor.py
lionchief/protocol.py
lionchief/sound.py
pyLionChief-1.0.0.dist-info/LICENSE
pyLionChief-1.0.0.dist-info/METADATA
pyLionChief-1.0.0.dist-info/WHEEL
pyLionChief-1.0.0.dist-info/top_level.txt
pyLionChief-1.0.0.dist-info/RECORD
