Metadata-Version: 2.1
Name: pyLionChief
Version: 1.0.0
Summary: Module for controlling Lionel LionChief series trains
Home-page: https://github.com/thetestgame/pyLionChief
Author: Jordan Maxwell
Maintainer: Jordan Maxwell
License: MIT
Classifier: Programming Language :: Python :: 3
License-File: LICENSE
